karman/__init__.py
karman/karman.py
karman/version.py
karman/bin/__init__.py
karman-1.0.1.data/scripts/karman
karman-1.0.1.dist-info/DESCRIPTION.rst
karman-1.0.1.dist-info/METADATA
karman-1.0.1.dist-info/RECORD
karman-1.0.1.dist-info/WHEEL
karman-1.0.1.dist-info/metadata.json
karman-1.0.1.dist-info/top_level.txt
